setup.py
test_pkg.py
fengkaibin-1.0.dist-info/METADATA
fengkaibin-1.0.dist-info/WHEEL
fengkaibin-1.0.dist-info/top_level.txt
fengkaibin-1.0.dist-info/RECORD
