Metadata-Version: 2.1
Name: fengkaibin
Version: 1.0
Summary: fengkaibin
Home-page: https://github.com
Author: myself and I
Author-email: fengkaibin@hotmail.com
License: MIT
Platform: UNKNOWN
